<?xml version="1.0" encoding="utf-8" ?><dwsync><file name="base-css.html" server="ftp.babycolt.com" local="3432049666" remote="12022690172" /><file name="components.html" server="ftp.babycolt.com" local="3432049666" remote="12022690172" /><file name="css3.html" server="ftp.babycolt.com" local="3432049666" remote="12022690232" /><file name="index.html" server="ftp.babycolt.com" local="3431519398" remote="12022690412" /><file name="intro.html" server="ftp.babycolt.com" local="3432049666" remote="12022690412" /><file name="javascript.html" server="ftp.babycolt.com" local="3432049666" remote="12022690412" /><file name="portfolio.html" server="ftp.babycolt.com" local="3432049666" remote="12022690472" /><file name="scaffolding.html" server="ftp.babycolt.com" local="3432049666" remote="12022690472" /><file name="slider.html" server="ftp.babycolt.com" local="3432049666" remote="12022690472" /><file name="social_media.html" server="ftp.babycolt.com" local="3432049666" remote="12022690472" /><file name="under_construction.html" server="ftp.babycolt.com" local="3432203432" remote="12022690472" /></dwsync>